pricelib/__init__.py
pricelib/common/__init__.py
pricelib/common/pricing_engine_base/__init__.py
pricelib/common/pricing_engine_base/analytic_engine_base.py
pricelib/common/pricing_engine_base/engine_base.py
pricelib/common/pricing_engine_base/mc_engine_base.py
pricelib/common/pricing_engine_base/pde_engine_base.py
pricelib/common/pricing_engine_base/quad_engine_base.py
pricelib/common/pricing_engine_base/tree_engine_base.py
pricelib/common/processes/__init__.py
pricelib/common/processes/bsm_process.py
pricelib/common/processes/heston_process.py
pricelib/common/processes/stoch_process.py
pricelib/common/product_base/__init__.py
pricelib/common/product_base/option_base.py
pricelib/common/term_structures/__init__.py
pricelib/common/term_structures/curve.py
pricelib/common/time/__init__.py
pricelib/common/time/calendars.py
pricelib/common/time/timeutils.py
pricelib/common/utilities/__init__.py
pricelib/common/utilities/enums.py
pricelib/common/utilities/numerical.py
pricelib/common/utilities/patterns.py
pricelib/common/utilities/pde_plot.py
pricelib/common/utilities/utility.py
pricelib/common/volmodels/__init__.py
pricelib/common/volmodels/constantvol.py
pricelib/common/volmodels/localvol.py
pricelib/common/volmodels/stochvolatility.py
pricelib/pricing_engines/__init__.py
pricelib/pricing_engines/analytic_engines/__init__.py
pricelib/pricing_engines/analytic_engines/analytic_airbag_engine.py
pricelib/pricing_engines/analytic_engines/analytic_asian_engine.py
pricelib/pricing_engines/analytic_engines/analytic_asset_or_nothing_engine.py
pricelib/pricing_engines/analytic_engines/analytic_barrier_engine.py
pricelib/pricing_engines/analytic_engines/analytic_cash_or_nothing_engine.py
pricelib/pricing_engines/analytic_engines/analytic_double_barrier_engine.py
pricelib/pricing_engines/analytic_engines/analytic_double_digital_engine.py
pricelib/pricing_engines/analytic_engines/analytic_double_shark_engine.py
pricelib-1.2.0.3.dist-info/LICENSE
pricelib-1.2.0.3.dist-info/METADATA
pricelib-1.2.0.3.dist-info/NOTICE
pricelib-1.2.0.3.dist-info/WHEEL
pricelib-1.2.0.3.dist-info/top_level.txt
pricelib-1.2.0.3.dist-info/RECORD
