Metadata-Version: 2.1
Name: pricelib
Version: 1.2.0.3
Summary: pricelib is an open-source financial derivatives pricing library written in Python.
Home-page: https://gitee.com/lltech/pricelib
Author: 上海凌瓴信息科技有限公司
Author-email: marx@galatech.com.cn
Classifier: Development Status :: 3 - Alpha
Classifier: Intended Audience :: Developers
Classifier: License :: OSI Approved :: Apache Software License
Classifier: Programming Language :: Python :: 3.8
Classifier: Programming Language :: Python :: 3.9
Classifier: Programming Language :: Python :: 3.10
Classifier: Programming Language :: Python :: 3.11
Classifier: Programming Language :: Python :: 3.12
License-File: LICENSE
License-File: NOTICE
Requires-Dist: numpy <=1.26.4,>=1.24.1
Requires-Dist: numba <=0.59.1,>=0.57.1
Requires-Dist: scipy <=1.13.0,>=1.8.0
Requires-Dist: pandas <=2.2.2,>=2.0.3
Requires-Dist: rocket-fft ~=0.2
Requires-Dist: importlib-metadata <=7.1.0,>=6.8.0
Requires-Dist: requests
Provides-Extra: dev
Requires-Dist: pytest ; extra == 'dev'
Requires-Dist: flake8 ; extra == 'dev'
Requires-Dist: pylint ; extra == 'dev'
Provides-Extra: plot
Requires-Dist: matplotlib <=3.7.5,>=3.5.3 ; extra == 'plot'
Requires-Dist: plotly <=5.22.0,>=5.16.1 ; extra == 'plot'
